.gitignore
.pylintrc
Makefile
README.rst
TODO.rst
USAGE.rst
distwago@.service
setup.cfg
setup.py
distkv_ext/wago/__init__.py
distkv_ext/wago/client.py
distkv_ext/wago/config.py
distkv_ext/wago/model.py
distkv_ext/wago/task.py
distkv_wago.egg-info/PKG-INFO
distkv_wago.egg-info/SOURCES.txt
distkv_wago.egg-info/dependency_links.txt
distkv_wago.egg-info/requires.txt
distkv_wago.egg-info/top_level.txt
distkv_wago.egg-info/zip-safe
tests/README
tests/__init__.py
tests/test_example.py